{"results": [{"test_file": "job0_fixture_setup", "status": "pass", "exit_code": 0, "start": 1587284025.5422442, "end": 1587284025.544197, "elapsed": 0.0019528865814208984}, {"test_file": "jstests\\core\\add_skip_stage_before_fetch.js", "status": "fail", "exit_code": 1, "start": 1587284025.5503142, "end": 1587284026.224802, "elapsed": 0.674487829208374}, {"test_file": "jstests\\core\\agg_hint.js", "status": "fail", "exit_code": 1, "start": 1587284026.2257795, "end": 1587284026.719879, "elapsed": 0.49409937858581543}, {"test_file": "jstests\\core\\aggregation_accepts_write_concern.js", "status": "fail", "exit_code": 1, "start": 1587284026.7218266, "end": 1587284027.1211956, "elapsed": 0.3993690013885498}, {"test_file": "jstests\\core\\aggregation_getmore_batchsize.js", "status": "fail", "exit_code": 1, "start": 1587284027.1221757, "end": 1587284027.519597, "elapsed": 0.39742136001586914}, {"test_file": "jstests\\core\\all.js", "status": "fail", "exit_code": 1, "start": 1587284027.5215514, "end": 1587284027.9970984, "elapsed": 0.47554707527160645}, {"test_file": "jstests\\core\\all2.js", "status": "fail", "exit_code": 1, "start": 1587284027.9980657, "end": 1587284028.4843593, "elapsed": 0.4862935543060303}, {"test_file": "jstests\\core\\all3.js", "status": "fail", "exit_code": 1, "start": 1587284028.4853354, "end": 1587284028.8573735, "elapsed": 0.3720381259918213}, {"test_file": "jstests\\core\\all4.js", "status": "fail", "exit_code": 1, "start": 1587284028.8583767, "end": 1587284029.302639, "elapsed": 0.4442622661590576}, {"test_file": "jstests\\core\\all5.js", "status": "fail", "exit_code": 1, "start": 1587284029.302639, "end": 1587284029.6224244, "elapsed": 0.31978535652160645}, {"test_file": "jstests\\core\\and.js", "status": "fail", "exit_code": 1, "start": 1587284029.6239018, "end": 1587284030.0169206, "elapsed": 0.3930187225341797}, {"test_file": "jstests\\core\\and2.js", "status": "fail", "exit_code": 1, "start": 1587284030.0178983, "end": 1587284030.317686, "elapsed": 0.2997877597808838}, {"test_file": "jstests\\core\\and3.js", "status": "fail", "exit_code": 1, "start": 1587284030.318657, "end": 1587284030.6477213, "elapsed": 0.32906436920166016}, {"test_file": "jstests\\core\\andor.js", "status": "fail", "exit_code": 1, "start": 1587284030.6487026, "end": 1587284031.0129406, "elapsed": 0.36423802375793457}, {"test_file": "jstests\\core\\apitest_db.js", "status": "fail", "exit_code": 1, "start": 1587284031.0139022, "end": 1587284031.3234391, "elapsed": 0.3095369338989258}, {"test_file": "jstests\\core\\apitest_db_profile_level.js", "status": "fail", "exit_code": 1, "start": 1587284031.3244216, "end": 1587284031.6046689, "elapsed": 0.28024721145629883}, {"test_file": "jstests\\core\\apitest_dbcollection.js", "status": "fail", "exit_code": 1, "start": 1587284031.6056495, "end": 1587284031.9278905, "elapsed": 0.32224106788635254}, {"test_file": "jstests\\core\\apply_ops1.js", "status": "fail", "exit_code": 1, "start": 1587284031.928863, "end": 1587284032.2755067, "elapsed": 0.34664368629455566}, {"test_file": "jstests\\core\\apply_ops2.js", "status": "fail", "exit_code": 1, "start": 1587284032.2764788, "end": 1587284032.6202047, "elapsed": 0.34372591972351074}, {"test_file": "jstests\\core\\apply_ops_dups.js", "status": "fail", "exit_code": 1, "start": 1587284032.6221604, "end": 1587284032.9258335, "elapsed": 0.30367302894592285}, {"test_file": "jstests\\core\\apply_ops_index_collation.js", "status": "fail", "exit_code": 1, "start": 1587284032.9268155, "end": 1587284033.2197614, "elapsed": 0.29294586181640625}, {"test_file": "apply_ops_index_collation:CleanEveryN", "status": "pass", "exit_code": 0, "start": 1587284033.2197614, "end": 1587284033.2207434, "elapsed": 0.000982046127319336}, {"test_file": "jstests\\core\\apply_ops_invalid_index_spec.js", "status": "fail", "exit_code": 1, "start": 1587284033.221716, "end": 1587284033.5585866, "elapsed": 0.3368706703186035}, {"test_file": "jstests\\core\\apply_ops_missing_field.js", "status": "fail", "exit_code": 1, "start": 1587284033.5595677, "end": 1587284033.876927, "elapsed": 0.31735920906066895}, {"test_file": "jstests\\core\\apply_ops_without_ns.js", "status": "fail", "exit_code": 1, "start": 1587284033.8779047, "end": 1587284034.1171353, "elapsed": 0.23923063278198242}, {"test_file": "jstests\\core\\array1.js", "status": "fail", "exit_code": 1, "start": 1587284034.118114, "end": 1587284034.4022698, "elapsed": 0.28415584564208984}, {"test_file": "jstests\\core\\array3.js", "status": "fail", "exit_code": 1, "start": 1587284034.4032576, "end": 1587284034.6805556, "elapsed": 0.2772979736328125}, {"test_file": "jstests\\core\\array4.js", "status": "fail", "exit_code": 1, "start": 1587284034.6805556, "end": 1587284034.908063, "elapsed": 0.2275073528289795}, {"test_file": "jstests\\core\\array_match1.js", "status": "fail", "exit_code": 1, "start": 1587284034.9090562, "end": 1587284035.1307003, "elapsed": 0.22164416313171387}, {"test_file": "jstests\\core\\array_match2.js", "status": "fail", "exit_code": 1, "start": 1587284035.1326706, "end": 1587284035.3679996, "elapsed": 0.23532891273498535}, {"test_file": "jstests\\core\\array_match3.js", "status": "fail", "exit_code": 1, "start": 1587284035.3689795, "end": 1587284035.6023486, "elapsed": 0.2333691120147705}, {"test_file": "jstests\\core\\array_match4.js", "status": "fail", "exit_code": 1, "start": 1587284035.603324, "end": 1587284035.8552444, "elapsed": 0.2519204616546631}, {"test_file": "jstests\\core\\arrayfind1.js", "status": "fail", "exit_code": 1, "start": 1587284035.8572128, "end": 1587284036.0915577, "elapsed": 0.2343449592590332}, {"test_file": "jstests\\core\\arrayfind2.js", "status": "fail", "exit_code": 1, "start": 1587284036.0925395, "end": 1587284036.328847, "elapsed": 0.23630738258361816}, {"test_file": "jstests\\core\\arrayfind3.js", "status": "fail", "exit_code": 1, "start": 1587284036.3298244, "end": 1587284036.681347, "elapsed": 0.35152244567871094}, {"test_file": "jstests\\core\\arrayfind4.js", "status": "fail", "exit_code": 1, "start": 1587284036.682321, "end": 1587284036.9137485, "elapsed": 0.23142743110656738}, {"test_file": "jstests\\core\\arrayfind5.js", "status": "fail", "exit_code": 1, "start": 1587284036.9147253, "end": 1587284037.1520362, "elapsed": 0.23731088638305664}, {"test_file": "jstests\\core\\arrayfind6.js", "status": "fail", "exit_code": 1, "start": 1587284037.1529896, "end": 1587284037.3756096, "elapsed": 0.22262001037597656}, {"test_file": "jstests\\core\\arrayfind7.js", "status": "fail", "exit_code": 1, "start": 1587284037.3765993, "end": 1587284037.669533, "elapsed": 0.29293370246887207}, {"test_file": "jstests\\core\\arrayfind8.js", "status": "fail", "exit_code": 1, "start": 1587284037.6705124, "end": 1587284037.9937212, "elapsed": 0.3232088088989258}, {"test_file": "jstests\\core\\arrayfind9.js", "status": "fail", "exit_code": 1, "start": 1587284037.994703, "end": 1587284038.2612696, "elapsed": 0.26656651496887207}, {"test_file": "jstests\\core\\arrayfinda.js", "status": "fail", "exit_code": 1, "start": 1587284038.26226, "end": 1587284038.4819536, "elapsed": 0.21969366073608398}, {"test_file": "arrayfinda:CleanEveryN", "status": "pass", "exit_code": 0, "start": 1587284038.482941, "end": 1587284038.482941, "elapsed": 0.0}, {"test_file": "jstests\\core\\arrayfindb.js", "status": "fail", "exit_code": 1, "start": 1587284038.4839191, "end": 1587284038.6987383, "elapsed": 0.21481919288635254}, {"test_file": "jstests\\core\\auth1.js", "status": "fail", "exit_code": 1, "start": 1587284038.6997125, "end": 1587284038.9135714, "elapsed": 0.21385884284973145}, {"test_file": "jstests\\core\\auth2.js", "status": "fail", "exit_code": 1, "start": 1587284038.9145424, "end": 1587284039.1313221, "elapsed": 0.2167797088623047}, {"test_file": "jstests\\core\\autocomplete.js", "status": "fail", "exit_code": 1, "start": 1587284039.1322982, "end": 1587284039.3685896, "elapsed": 0.23629140853881836}, {"test_file": "jstests\\core\\autoid.js", "status": "fail", "exit_code": 1, "start": 1587284039.369581, "end": 1587284039.5843909, "elapsed": 0.21480989456176758}, {"test_file": "jstests\\core\\automation_setparameter.js", "status": "fail", "exit_code": 1, "start": 1587284039.585378, "end": 1587284039.8109329, "elapsed": 0.2255549430847168}, {"test_file": "jstests\\core\\awaitdata_getmore_cmd.js", "status": "fail", "exit_code": 1, "start": 1587284039.8119228, "end": 1587284040.043336, "elapsed": 0.2314131259918213}, {"test_file": "job0_fixture_teardown", "status": "pass", "exit_code": 0, "start": 1587284040.043336, "end": 1587284040.044316, "elapsed": 0.0009801387786865234}], "failures": 47}