{"results": [{"test_file": "job0_fixture_setup", "status": "pass", "exit_code": 0, "start": 1587162826.4967573, "end": 1587162826.4996762, "elapsed": 0.0029189586639404297}, {"test_file": "jstests\\core\\add_skip_stage_before_fetch.js", "status": "fail", "exit_code": 4294967293, "start": 1587162826.501639, "end": 1587162831.2347188, "elapsed": 4.73307991027832}, {"test_file": "jstests\\core\\agg_hint.js", "status": "fail", "exit_code": 4294967293, "start": 1587162831.2356887, "end": 1587162831.698548, "elapsed": 0.4628593921661377}, {"test_file": "jstests\\core\\aggregation_accepts_write_concern.js", "status": "pass", "exit_code": 0, "start": 1587162831.7005067, "end": 1587162834.8907347, "elapsed": 3.19022798538208}, {"test_file": "jstests\\core\\aggregation_getmore_batchsize.js", "status": "fail", "exit_code": 4294967293, "start": 1587162834.8917093, "end": 1587162835.6816854, "elapsed": 0.7899761199951172}, {"test_file": "jstests\\core\\all.js", "status": "fail", "exit_code": 4294967293, "start": 1587162835.6836402, "end": 1587162836.3720803, "elapsed": 0.6884400844573975}, {"test_file": "jstests\\core\\all2.js", "status": "pass", "exit_code": 0, "start": 1587162836.3730564, "end": 1587162842.154896, "elapsed": 5.781839609146118}, {"test_file": "jstests\\core\\all3.js", "status": "pass", "exit_code": 0, "start": 1587162842.1558774, "end": 1587162843.1606817, "elapsed": 1.0048043727874756}, {"test_file": "jstests\\core\\all4.js", "status": "pass", "exit_code": 0, "start": 1587162843.1616745, "end": 1587162844.1635628, "elapsed": 1.0018882751464844}, {"test_file": "jstests\\core\\all5.js", "status": "pass", "exit_code": 0, "start": 1587162844.1645317, "end": 1587162848.8927274, "elapsed": 4.728195667266846}, {"test_file": "jstests\\core\\and.js", "status": "fail", "exit_code": 4294967293, "start": 1587162848.8937075, "end": 1587162849.8467855, "elapsed": 0.953078031539917}, {"test_file": "jstests\\core\\and2.js", "status": "pass", "exit_code": 0, "start": 1587162849.8477442, "end": 1587162851.7128649, "elapsed": 1.8651206493377686}, {"test_file": "jstests\\core\\and3.js", "status": "fail", "exit_code": 4294967293, "start": 1587162851.7138433, "end": 1587162853.2986865, "elapsed": 1.5848431587219238}, {"test_file": "jstests\\core\\andor.js", "status": "pass", "exit_code": 0, "start": 1587162853.3006558, "end": 1587162855.6588874, "elapsed": 2.358231544494629}, {"test_file": "jstests\\core\\apitest_db.js", "status": "fail", "exit_code": 4294967293, "start": 1587162855.6598644, "end": 1587162855.9567263, "elapsed": 0.2968618869781494}, {"test_file": "jstests\\core\\apitest_db_profile_level.js", "status": "fail", "exit_code": 4294967293, "start": 1587162855.957706, "end": 1587162856.2330604, "elapsed": 0.27535438537597656}, {"test_file": "jstests\\core\\apitest_dbcollection.js", "status": "fail", "exit_code": 4294967293, "start": 1587162856.2340457, "end": 1587162858.493666, "elapsed": 2.259620189666748}, {"test_file": "jstests\\core\\apply_ops1.js", "status": "fail", "exit_code": 4294967293, "start": 1587162858.4946437, "end": 1587162858.7778153, "elapsed": 0.2831716537475586}, {"test_file": "jstests\\core\\apply_ops2.js", "status": "fail", "exit_code": 4294967293, "start": 1587162858.7788064, "end": 1587162859.3754385, "elapsed": 0.5966320037841797}, {"test_file": "jstests\\core\\apply_ops_dups.js", "status": "fail", "exit_code": 4294967293, "start": 1587162859.3764327, "end": 1587162859.9369245, "elapsed": 0.5604918003082275}, {"test_file": "jstests\\core\\apply_ops_index_collation.js", "status": "fail", "exit_code": 4294967293, "start": 1587162859.9379063, "end": 1587162860.415405, "elapsed": 0.47749876976013184}, {"test_file": "apply_ops_index_collation:CleanEveryN", "status": "pass", "exit_code": 0, "start": 1587162860.415405, "end": 1587162860.4163895, "elapsed": 0.0009844303131103516}, {"test_file": "jstests\\core\\apply_ops_invalid_index_spec.js", "status": "fail", "exit_code": 4294967293, "start": 1587162860.4173687, "end": 1587162860.9563997, "elapsed": 0.5390310287475586}, {"test_file": "jstests\\core\\apply_ops_missing_field.js", "status": "fail", "exit_code": 4294967293, "start": 1587162860.957379, "end": 1587162861.5266533, "elapsed": 0.5692741870880127}, {"test_file": "jstests\\core\\apply_ops_without_ns.js", "status": "pass", "exit_code": 0, "start": 1587162861.5276513, "end": 1587162861.7981365, "elapsed": 0.27048516273498535}, {"test_file": "jstests\\core\\array1.js", "status": "pass", "exit_code": 0, "start": 1587162861.799118, "end": 1587162863.3937447, "elapsed": 1.5946266651153564}, {"test_file": "jstests\\core\\array3.js", "status": "pass", "exit_code": 0, "start": 1587162863.395693, "end": 1587162863.681812, "elapsed": 0.2861189842224121}, {"test_file": "jstests\\core\\array4.js", "status": "pass", "exit_code": 0, "start": 1587162863.6827807, "end": 1587162864.9405003, "elapsed": 1.2577195167541504}, {"test_file": "jstests\\core\\array_match1.js", "status": "pass", "exit_code": 0, "start": 1587162864.9414866, "end": 1587162868.0037782, "elapsed": 3.0622916221618652}, {"test_file": "jstests\\core\\array_match2.js", "status": "pass", "exit_code": 0, "start": 1587162868.0047596, "end": 1587162868.568187, "elapsed": 0.5634274482727051}, {"test_file": "jstests\\core\\array_match3.js", "status": "pass", "exit_code": 0, "start": 1587162868.5691707, "end": 1587162870.1510925, "elapsed": 1.5819218158721924}, {"test_file": "jstests\\core\\array_match4.js", "status": "fail", "exit_code": 4294967293, "start": 1587162870.153064, "end": 1587162870.681326, "elapsed": 0.5282618999481201}, {"test_file": "jstests\\core\\arrayfind1.js", "status": "pass", "exit_code": 0, "start": 1587162870.6823285, "end": 1587162872.4029052, "elapsed": 1.7205767631530762}, {"test_file": "jstests\\core\\arrayfind2.js", "status": "fail", "exit_code": 4294967293, "start": 1587162872.403884, "end": 1587162873.0327535, "elapsed": 0.6288695335388184}, {"test_file": "jstests\\core\\arrayfind3.js", "status": "fail", "exit_code": 4294967293, "start": 1587162873.0337188, "end": 1587162873.6332834, "elapsed": 0.5995645523071289}, {"test_file": "jstests\\core\\arrayfind4.js", "status": "fail", "exit_code": 4294967293, "start": 1587162873.6342757, "end": 1587162874.135206, "elapsed": 0.5009303092956543}, {"test_file": "jstests\\core\\arrayfind5.js", "status": "fail", "exit_code": 4294967293, "start": 1587162874.1371732, "end": 1587162874.5375352, "elapsed": 0.4003620147705078}, {"test_file": "jstests\\core\\arrayfind6.js", "status": "fail", "exit_code": 4294967293, "start": 1587162874.5385115, "end": 1587162874.952534, "elapsed": 0.41402244567871094}, {"test_file": "jstests\\core\\arrayfind7.js", "status": "fail", "exit_code": 4294967293, "start": 1587162874.9545007, "end": 1587162875.3773026, "elapsed": 0.4228019714355469}, {"test_file": "jstests\\core\\arrayfind8.js", "status": "fail", "exit_code": 4294967293, "start": 1587162875.3783035, "end": 1587162875.7796276, "elapsed": 0.4013240337371826}, {"test_file": "jstests\\core\\arrayfind9.js", "status": "fail", "exit_code": 4294967293, "start": 1587162875.7806175, "end": 1587162876.1575317, "elapsed": 0.37691426277160645}, {"test_file": "jstests\\core\\arrayfinda.js", "status": "fail", "exit_code": 4294967293, "start": 1587162876.1585112, "end": 1587162876.6692176, "elapsed": 0.5107064247131348}, {"test_file": "arrayfinda:CleanEveryN", "status": "pass", "exit_code": 0, "start": 1587162876.6702104, "end": 1587162876.6702104, "elapsed": 0.0}, {"test_file": "jstests\\core\\arrayfindb.js", "status": "fail", "exit_code": 4294967293, "start": 1587162876.6711926, "end": 1587162877.3810916, "elapsed": 0.7098989486694336}, {"test_file": "jstests\\core\\auth1.js", "status": "fail", "exit_code": 4294967293, "start": 1587162877.3820722, "end": 1587162877.6730587, "elapsed": 0.2909865379333496}, {"test_file": "jstests\\core\\auth2.js", "status": "pass", "exit_code": 0, "start": 1587162877.6740506, "end": 1587162877.9455044, "elapsed": 0.271453857421875}, {"test_file": "jstests\\core\\autocomplete.js", "status": "fail", "exit_code": 4294967293, "start": 1587162877.9464855, "end": 1587162878.381025, "elapsed": 0.4345395565032959}, {"test_file": "jstests\\core\\autoid.js", "status": "fail", "exit_code": 4294967293, "start": 1587162878.382006, "end": 1587162878.8253248, "elapsed": 0.44331884384155273}, {"test_file": "jstests\\core\\automation_setparameter.js", "status": "fail", "exit_code": 4294967293, "start": 1587162878.8263164, "end": 1587162879.1153507, "elapsed": 0.289034366607666}, {"test_file": "jstests\\core\\awaitdata_getmore_cmd.js", "status": "fail", "exit_code": 4294967293, "start": 1587162879.1163325, "end": 1587162879.4766543, "elapsed": 0.3603217601776123}, {"test_file": "job0_fixture_teardown", "status": "pass", "exit_code": 0, "start": 1587162879.477642, "end": 1587162879.4786024, "elapsed": 0.0009603500366210938}], "failures": 31}