{"results": [{"test_file": "job0_fixture_setup", "status": "pass", "exit_code": 0, "start": 1587011967.8441448, "end": 1587011967.8451276, "elapsed": 0.0009827613830566406}, {"test_file": "jstests\\core\\add_skip_stage_before_fetch.js", "status": "fail", "exit_code": 1, "start": 1587011967.8461041, "end": 1587011968.630202, "elapsed": 0.7840979099273682}, {"test_file": "jstests\\core\\agg_hint.js", "status": "fail", "exit_code": 1, "start": 1587011968.6311767, "end": 1587011969.1360097, "elapsed": 0.5048329830169678}, {"test_file": "jstests\\core\\aggregation_accepts_write_concern.js", "status": "fail", "exit_code": 1, "start": 1587011969.1369956, "end": 1587011969.5373485, "elapsed": 0.40035295486450195}, {"test_file": "jstests\\core\\aggregation_getmore_batchsize.js", "status": "fail", "exit_code": 1, "start": 1587011969.5383306, "end": 1587011969.953319, "elapsed": 0.41498851776123047}, {"test_file": "jstests\\core\\all.js", "status": "fail", "exit_code": 1, "start": 1587011969.9543052, "end": 1587011970.3468537, "elapsed": 0.3925485610961914}, {"test_file": "jstests\\core\\all2.js", "status": "fail", "exit_code": 1, "start": 1587011970.3497775, "end": 1587011970.7823553, "elapsed": 0.43257784843444824}, {"test_file": "jstests\\core\\all3.js", "status": "fail", "exit_code": 1, "start": 1587011970.7921143, "end": 1587011971.2324958, "elapsed": 0.4403815269470215}, {"test_file": "jstests\\core\\all4.js", "status": "fail", "exit_code": 1, "start": 1587011971.240328, "end": 1587011971.6143005, "elapsed": 0.37397241592407227}, {"test_file": "jstests\\core\\all5.js", "status": "fail", "exit_code": 1, "start": 1587011971.6162605, "end": 1587011971.9599686, "elapsed": 0.3437080383300781}, {"test_file": "jstests\\core\\and.js", "status": "fail", "exit_code": 1, "start": 1587011971.9609454, "end": 1587011972.328098, "elapsed": 0.36715269088745117}, {"test_file": "jstests\\core\\and2.js", "status": "fail", "exit_code": 1, "start": 1587011972.3290768, "end": 1587011972.6727848, "elapsed": 0.3437080383300781}, {"test_file": "jstests\\core\\and3.js", "status": "fail", "exit_code": 1, "start": 1587011972.6737652, "end": 1587011972.9715927, "elapsed": 0.29782748222351074}, {"test_file": "jstests\\core\\andor.js", "status": "fail", "exit_code": 1, "start": 1587011972.9725838, "end": 1587011973.2645254, "elapsed": 0.29194164276123047}, {"test_file": "jstests\\core\\apitest_db.js", "status": "fail", "exit_code": 1, "start": 1587011973.2655177, "end": 1587011973.5760314, "elapsed": 0.3105137348175049}, {"test_file": "jstests\\core\\apitest_db_profile_level.js", "status": "fail", "exit_code": 1, "start": 1587011973.5779989, "end": 1587011973.8709195, "elapsed": 0.2929205894470215}, {"test_file": "jstests\\core\\apitest_dbcollection.js", "status": "fail", "exit_code": 1, "start": 1587011973.8719, "end": 1587011974.2195358, "elapsed": 0.34763574600219727}, {"test_file": "jstests\\core\\apply_ops1.js", "status": "fail", "exit_code": 1, "start": 1587011974.2205114, "end": 1587011974.5935133, "elapsed": 0.3730018138885498}, {"test_file": "jstests\\core\\apply_ops2.js", "status": "fail", "exit_code": 1, "start": 1587011974.595462, "end": 1587011974.8952315, "elapsed": 0.29976940155029297}, {"test_file": "jstests\\core\\apply_ops_dups.js", "status": "fail", "exit_code": 1, "start": 1587011974.896208, "end": 1587011975.135446, "elapsed": 0.23923802375793457}, {"test_file": "jstests\\core\\apply_ops_index_collation.js", "status": "fail", "exit_code": 1, "start": 1587011975.1364348, "end": 1587011975.3761523, "elapsed": 0.2397174835205078}, {"test_file": "apply_ops_index_collation:CleanEveryN", "status": "pass", "exit_code": 0, "start": 1587011975.3766441, "end": 1587011975.3766441, "elapsed": 0.0}, {"test_file": "jstests\\core\\apply_ops_invalid_index_spec.js", "status": "fail", "exit_code": 1, "start": 1587011975.3781097, "end": 1587011975.659325, "elapsed": 0.28121519088745117}, {"test_file": "jstests\\core\\apply_ops_missing_field.js", "status": "fail", "exit_code": 1, "start": 1587011975.6603096, "end": 1587011975.9297986, "elapsed": 0.269489049911499}, {"test_file": "jstests\\core\\apply_ops_without_ns.js", "status": "fail", "exit_code": 1, "start": 1587011975.9307895, "end": 1587011976.163173, "elapsed": 0.23238348960876465}, {"test_file": "jstests\\core\\array1.js", "status": "fail", "exit_code": 1, "start": 1587011976.1651433, "end": 1587011976.399476, "elapsed": 0.23433279991149902}, {"test_file": "jstests\\core\\array3.js", "status": "fail", "exit_code": 1, "start": 1587011976.4004571, "end": 1587011976.6348135, "elapsed": 0.23435640335083008}, {"test_file": "jstests\\core\\array4.js", "status": "fail", "exit_code": 1, "start": 1587011976.6358016, "end": 1587011976.9316704, "elapsed": 0.2958688735961914}, {"test_file": "jstests\\core\\array_match1.js", "status": "fail", "exit_code": 1, "start": 1587011976.9326432, "end": 1587011977.1611378, "elapsed": 0.22849464416503906}, {"test_file": "jstests\\core\\array_match2.js", "status": "fail", "exit_code": 1, "start": 1587011977.1631038, "end": 1587011977.384739, "elapsed": 0.221635103225708}, {"test_file": "jstests\\core\\array_match3.js", "status": "fail", "exit_code": 1, "start": 1587011977.3857353, "end": 1587011977.6142077, "elapsed": 0.22847247123718262}, {"test_file": "jstests\\core\\array_match4.js", "status": "fail", "exit_code": 1, "start": 1587011977.615203, "end": 1587011977.9247367, "elapsed": 0.30953383445739746}, {"test_file": "jstests\\core\\arrayfind1.js", "status": "fail", "exit_code": 1, "start": 1587011977.9257104, "end": 1587011978.178627, "elapsed": 0.2529165744781494}, {"test_file": "jstests\\core\\arrayfind2.js", "status": "fail", "exit_code": 1, "start": 1587011978.1796093, "end": 1587011978.435419, "elapsed": 0.2558097839355469}, {"test_file": "jstests\\core\\arrayfind3.js", "status": "fail", "exit_code": 1, "start": 1587011978.4364135, "end": 1587011978.671736, "elapsed": 0.2353224754333496}, {"test_file": "jstests\\core\\arrayfind4.js", "status": "fail", "exit_code": 1, "start": 1587011978.6727185, "end": 1587011978.9373407, "elapsed": 0.26462221145629883}, {"test_file": "jstests\\core\\arrayfind5.js", "status": "fail", "exit_code": 1, "start": 1587011978.9383166, "end": 1587011979.1804745, "elapsed": 0.2421579360961914}, {"test_file": "jstests\\core\\arrayfind6.js", "status": "fail", "exit_code": 1, "start": 1587011979.1814477, "end": 1587011979.4040875, "elapsed": 0.222639799118042}, {"test_file": "jstests\\core\\arrayfind7.js", "status": "fail", "exit_code": 1, "start": 1587011979.4050732, "end": 1587011979.7087429, "elapsed": 0.30366969108581543}, {"test_file": "jstests\\core\\arrayfind8.js", "status": "fail", "exit_code": 1, "start": 1587011979.7097116, "end": 1587011980.0309927, "elapsed": 0.32128119468688965}, {"test_file": "jstests\\core\\arrayfind9.js", "status": "fail", "exit_code": 1, "start": 1587011980.0319643, "end": 1587011980.2711837, "elapsed": 0.23921942710876465}, {"test_file": "jstests\\core\\arrayfinda.js", "status": "fail", "exit_code": 1, "start": 1587011980.2731547, "end": 1587011980.504558, "elapsed": 0.23140335083007812}, {"test_file": "arrayfinda:CleanEveryN", "status": "pass", "exit_code": 0, "start": 1587011980.5055537, "end": 1587011980.5055537, "elapsed": 0.0}, {"test_file": "jstests\\core\\arrayfindb.js", "status": "fail", "exit_code": 1, "start": 1587011980.506528, "end": 1587011980.744778, "elapsed": 0.2382500171661377}, {"test_file": "jstests\\core\\auth1.js", "status": "fail", "exit_code": 1, "start": 1587011980.7457602, "end": 1587011980.9752169, "elapsed": 0.22945666313171387}, {"test_file": "jstests\\core\\auth2.js", "status": "fail", "exit_code": 1, "start": 1587011980.9762123, "end": 1587011981.201768, "elapsed": 0.2255556583404541}, {"test_file": "jstests\\core\\autocomplete.js", "status": "fail", "exit_code": 1, "start": 1587011981.2027528, "end": 1587011981.4185507, "elapsed": 0.21579790115356445}, {"test_file": "jstests\\core\\autoid.js", "status": "fail", "exit_code": 1, "start": 1587011981.4195337, "end": 1587011981.6519158, "elapsed": 0.23238205909729004}, {"test_file": "jstests\\core\\automation_setparameter.js", "status": "fail", "exit_code": 1, "start": 1587011981.6538858, "end": 1587011981.8794348, "elapsed": 0.22554898262023926}, {"test_file": "jstests\\core\\awaitdata_getmore_cmd.js", "status": "fail", "exit_code": 1, "start": 1587011981.8813925, "end": 1587011982.1176898, "elapsed": 0.2362973690032959}, {"test_file": "job0_fixture_teardown", "status": "pass", "exit_code": 0, "start": 1587011982.1176898, "end": 1587011982.1186764, "elapsed": 0.0009865760803222656}], "failures": 47}