{"results": [{"test_file": "job0_fixture_setup", "status": "pass", "exit_code": 0, "start": 1587072078.288772, "end": 1587072078.2897444, "elapsed": 0.0009722709655761719}, {"test_file": "jstests\\core\\add_skip_stage_before_fetch.js", "status": "fail", "exit_code": 1, "start": 1587072078.2907248, "end": 1587072079.0250585, "elapsed": 0.7343337535858154}, {"test_file": "jstests\\core\\agg_hint.js", "status": "fail", "exit_code": 1, "start": 1587072079.0279806, "end": 1587072079.650014, "elapsed": 0.6220333576202393}, {"test_file": "jstests\\core\\aggregation_accepts_write_concern.js", "status": "fail", "exit_code": 1, "start": 1587072079.6509888, "end": 1587072080.066005, "elapsed": 0.41501617431640625}, {"test_file": "jstests\\core\\aggregation_getmore_batchsize.js", "status": "fail", "exit_code": 1, "start": 1587072080.0728426, "end": 1587072080.571822, "elapsed": 0.4989793300628662}, {"test_file": "jstests\\core\\all.js", "status": "fail", "exit_code": 1, "start": 1587072080.5757358, "end": 1587072081.0337186, "elapsed": 0.45798277854919434}, {"test_file": "jstests\\core\\all2.js", "status": "fail", "exit_code": 1, "start": 1587072081.0346968, "end": 1587072081.3598592, "elapsed": 0.325162410736084}, {"test_file": "jstests\\core\\all3.js", "status": "fail", "exit_code": 1, "start": 1587072081.360832, "end": 1587072081.6821072, "elapsed": 0.3212752342224121}, {"test_file": "jstests\\core\\all4.js", "status": "fail", "exit_code": 1, "start": 1587072081.6860125, "end": 1587072082.0248628, "elapsed": 0.3388502597808838}, {"test_file": "jstests\\core\\all5.js", "status": "fail", "exit_code": 1, "start": 1587072082.0268252, "end": 1587072082.406663, "elapsed": 0.3798377513885498}, {"test_file": "jstests\\core\\and.js", "status": "fail", "exit_code": 1, "start": 1587072082.4076452, "end": 1587072082.7328186, "elapsed": 0.32517337799072266}, {"test_file": "jstests\\core\\and2.js", "status": "fail", "exit_code": 1, "start": 1587072082.7337976, "end": 1587072083.0921683, "elapsed": 0.3583707809448242}, {"test_file": "jstests\\core\\and3.js", "status": "fail", "exit_code": 1, "start": 1587072083.0931478, "end": 1587072083.3812096, "elapsed": 0.28806185722351074}, {"test_file": "jstests\\core\\andor.js", "status": "fail", "exit_code": 1, "start": 1587072083.3821878, "end": 1587072083.718098, "elapsed": 0.3359100818634033}, {"test_file": "jstests\\core\\apitest_db.js", "status": "fail", "exit_code": 1, "start": 1587072083.7190945, "end": 1587072084.0071592, "elapsed": 0.28806471824645996}, {"test_file": "jstests\\core\\apitest_db_profile_level.js", "status": "fail", "exit_code": 1, "start": 1587072084.0081265, "end": 1587072084.3274386, "elapsed": 0.31931209564208984}, {"test_file": "jstests\\core\\apitest_dbcollection.js", "status": "fail", "exit_code": 1, "start": 1587072084.328418, "end": 1587072084.597917, "elapsed": 0.2694990634918213}, {"test_file": "jstests\\core\\apply_ops1.js", "status": "fail", "exit_code": 1, "start": 1587072084.598911, "end": 1587072084.976804, "elapsed": 0.37789297103881836}, {"test_file": "jstests\\core\\apply_ops2.js", "status": "fail", "exit_code": 1, "start": 1587072084.9777904, "end": 1587072085.2443633, "elapsed": 0.2665729522705078}, {"test_file": "jstests\\core\\apply_ops_dups.js", "status": "fail", "exit_code": 1, "start": 1587072085.2453423, "end": 1587072085.4914463, "elapsed": 0.24610400199890137}, {"test_file": "jstests\\core\\apply_ops_index_collation.js", "status": "fail", "exit_code": 1, "start": 1587072085.4923928, "end": 1587072085.737493, "elapsed": 0.2451002597808838}, {"test_file": "apply_ops_index_collation:CleanEveryN", "status": "pass", "exit_code": 0, "start": 1587072085.7384977, "end": 1587072085.7384977, "elapsed": 0.0}, {"test_file": "jstests\\core\\apply_ops_invalid_index_spec.js", "status": "fail", "exit_code": 1, "start": 1587072085.739455, "end": 1587072086.042167, "elapsed": 0.30271196365356445}, {"test_file": "jstests\\core\\apply_ops_missing_field.js", "status": "fail", "exit_code": 1, "start": 1587072086.043139, "end": 1587072086.2696853, "elapsed": 0.2265462875366211}, {"test_file": "jstests\\core\\apply_ops_without_ns.js", "status": "fail", "exit_code": 1, "start": 1587072086.271641, "end": 1587072086.4933066, "elapsed": 0.221665620803833}, {"test_file": "jstests\\core\\array1.js", "status": "fail", "exit_code": 1, "start": 1587072086.4942865, "end": 1587072086.7520697, "elapsed": 0.2577831745147705}, {"test_file": "jstests\\core\\array3.js", "status": "fail", "exit_code": 1, "start": 1587072086.7530677, "end": 1587072087.0958107, "elapsed": 0.342742919921875}, {"test_file": "jstests\\core\\array4.js", "status": "fail", "exit_code": 1, "start": 1587072087.0967813, "end": 1587072087.331161, "elapsed": 0.23437976837158203}, {"test_file": "jstests\\core\\array_match1.js", "status": "fail", "exit_code": 1, "start": 1587072087.3321464, "end": 1587072087.561586, "elapsed": 0.22943949699401855}, {"test_file": "jstests\\core\\array_match2.js", "status": "fail", "exit_code": 1, "start": 1587072087.563556, "end": 1587072087.813555, "elapsed": 0.2499990463256836}, {"test_file": "jstests\\core\\array_match3.js", "status": "fail", "exit_code": 1, "start": 1587072087.8155077, "end": 1587072088.0566804, "elapsed": 0.24117279052734375}, {"test_file": "jstests\\core\\array_match4.js", "status": "fail", "exit_code": 1, "start": 1587072088.0576642, "end": 1587072088.2930002, "elapsed": 0.2353360652923584}, {"test_file": "jstests\\core\\arrayfind1.js", "status": "fail", "exit_code": 1, "start": 1587072088.2939787, "end": 1587072088.5293038, "elapsed": 0.23532509803771973}, {"test_file": "jstests\\core\\arrayfind2.js", "status": "fail", "exit_code": 1, "start": 1587072088.5302908, "end": 1587072088.807606, "elapsed": 0.2773151397705078}, {"test_file": "jstests\\core\\arrayfind3.js", "status": "fail", "exit_code": 1, "start": 1587072088.8086295, "end": 1587072089.1581626, "elapsed": 0.3495330810546875}, {"test_file": "jstests\\core\\arrayfind4.js", "status": "fail", "exit_code": 1, "start": 1587072089.1591442, "end": 1587072089.3886256, "elapsed": 0.22948145866394043}, {"test_file": "jstests\\core\\arrayfind5.js", "status": "fail", "exit_code": 1, "start": 1587072089.3895967, "end": 1587072089.6200423, "elapsed": 0.23044562339782715}, {"test_file": "jstests\\core\\arrayfind6.js", "status": "fail", "exit_code": 1, "start": 1587072089.6210244, "end": 1587072089.8417053, "elapsed": 0.22068095207214355}, {"test_file": "jstests\\core\\arrayfind7.js", "status": "fail", "exit_code": 1, "start": 1587072089.8427026, "end": 1587072090.1190364, "elapsed": 0.2763338088989258}, {"test_file": "jstests\\core\\arrayfind8.js", "status": "fail", "exit_code": 1, "start": 1587072090.120016, "end": 1587072090.4315135, "elapsed": 0.31149744987487793}, {"test_file": "jstests\\core\\arrayfind9.js", "status": "fail", "exit_code": 1, "start": 1587072090.4324968, "end": 1587072090.6941836, "elapsed": 0.2616868019104004}, {"test_file": "jstests\\core\\arrayfinda.js", "status": "fail", "exit_code": 1, "start": 1587072090.6961536, "end": 1587072090.9158628, "elapsed": 0.21970915794372559}, {"test_file": "arrayfinda:CleanEveryN", "status": "pass", "exit_code": 0, "start": 1587072090.9158628, "end": 1587072090.9168482, "elapsed": 0.0009853839874267578}, {"test_file": "jstests\\core\\arrayfindb.js", "status": "fail", "exit_code": 1, "start": 1587072090.9178188, "end": 1587072091.131666, "elapsed": 0.21384716033935547}, {"test_file": "jstests\\core\\auth1.js", "status": "fail", "exit_code": 1, "start": 1587072091.1326475, "end": 1587072091.355282, "elapsed": 0.22263455390930176}, {"test_file": "jstests\\core\\auth2.js", "status": "fail", "exit_code": 1, "start": 1587072091.356265, "end": 1587072091.5896466, "elapsed": 0.2333815097808838}, {"test_file": "jstests\\core\\autocomplete.js", "status": "fail", "exit_code": 1, "start": 1587072091.5906255, "end": 1587072091.802529, "elapsed": 0.21190357208251953}, {"test_file": "jstests\\core\\autoid.js", "status": "fail", "exit_code": 1, "start": 1587072091.8035023, "end": 1587072092.0134397, "elapsed": 0.20993733406066895}, {"test_file": "jstests\\core\\automation_setparameter.js", "status": "fail", "exit_code": 1, "start": 1587072092.0144188, "end": 1587072092.2263067, "elapsed": 0.21188783645629883}, {"test_file": "jstests\\core\\awaitdata_getmore_cmd.js", "status": "fail", "exit_code": 1, "start": 1587072092.2272906, "end": 1587072092.45384, "elapsed": 0.22654938697814941}, {"test_file": "job0_fixture_teardown", "status": "pass", "exit_code": 0, "start": 1587072092.4548252, "end": 1587072092.4548252, "elapsed": 0.0}], "failures": 47}